lmod_ingest/__init__.py
lmod_ingest/main.py
lmod_ingest/migrations/env.py
lmod_ingest/migrations/versions/0_1.py
lmod_ingest/migrations/versions/0_2.py
lmod_ingest/utils.py
lmod_ingest-0.4.6.dist-info/LICENSE
lmod_ingest-0.4.6.dist-info/METADATA
lmod_ingest-0.4.6.dist-info/WHEEL
lmod_ingest-0.4.6.dist-info/entry_points.txt
lmod_ingest-0.4.6.dist-info/RECORD
