Metadata-Version: 2.3
Name: lmod-ingest
Version: 0.4.6
Summary: Data ingestion utility for loading Lmod usage logs into a database.
License: GPLv3
Author: Pitt Center for Research Computing
Requires-Python: >=3.9,<4.0
Classifier: Environment :: Console
Classifier: Intended Audience :: System Administrators
Classifier: License :: OSI Approved :: GNU General Public License v3 (GPLv3)
Classifier: License :: Other/Proprietary License
Classifier: Natural Language :: English
Classifier: Operating System :: POSIX :: Linux
Classifier: Programming Language :: Python :: 3
Classifier: Programming Language :: Python :: 3.9
Classifier: Programming Language :: Python :: 3.10
Classifier: Programming Language :: Python :: 3.11
Classifier: Programming Language :: Python :: 3.12
Classifier: Programming Language :: Python :: 3.13
Classifier: Topic :: Database
Classifier: Topic :: System :: Monitoring
Classifier: Typing :: Typed
Requires-Dist: alembic (==1.16.2)
Requires-Dist: asyncpg (==0.30.0)
Requires-Dist: pandas (==2.3.0)
Requires-Dist: python-dotenv (==1.1.1)
Requires-Dist: sqlalchemy (==2.0.41)
Project-URL: Homepage, https://github.com/pitt-crc/lmod_tracking
Project-URL: Repository, https://github.com/pitt-crc/lmod_tracking
